pycord_rest/__init__.py
pycord_rest/_version.py
pycord_rest/app.py
pycord_rest/errors.py
pycord_rest/models.py
pycord_rest/py.typed
pycord_rest_bot-0.1.3.dist-info/METADATA
pycord_rest_bot-0.1.3.dist-info/WHEEL
pycord_rest_bot-0.1.3.dist-info/licenses/LICENSE
pycord_rest_bot-0.1.3.dist-info/RECORD
