Metadata-Version: 2.4
Name: pycord-rest-bot
Version: 0.1.3
Summary: A lightweight wrapper for Discord's HTTP interactions and webhook events using py-cord and FastAPI
Project-URL: Homepage, https://github.com/Paillat-dev/pycord-rest
Project-URL: source_archive, https://github.com/Paillat-dev/pycord-rest/archive/a63e620aad53c2b3b40ea75de5a18958407fdc32.zip
Author-email: Paillat-dev <me@paillat.dev>
License-Expression: MIT
License-File: LICENSE
Keywords: bot,discord,pycord,rest
Classifier: Development Status :: 3 - Alpha
Classifier: Intended Audience :: Developers
Classifier: License :: OSI Approved :: MIT License
Classifier: Operating System :: OS Independent
Classifier: Programming Language :: Python :: 3 :: Only
Classifier: Programming Language :: Python :: 3.12
Classifier: Typing :: Typed
Requires-Python: ==3.12.*
Requires-Dist: fastapi>=0.115.11
Requires-Dist: orjson>=3.10.15
Requires-Dist: py-cord>=2.7.0rc1
Requires-Dist: pynacl>=1.5.0
Requires-Dist: uvicorn>=0.34.0
